cryptos/__init__.py
cryptos/blocks.py
cryptos/composite.py
cryptos/constants.py
cryptos/deterministic.py
cryptos/english.txt
cryptos/keystore.py
cryptos/main.py
cryptos/mnemonic.py
cryptos/py2specials.py
cryptos/py3specials.py
cryptos/ripemd.py
cryptos/segwit_addr.py
cryptos/stealth.py
cryptos/transaction.py
cryptos/wallet.py
cryptos/wallet_utils.py
cryptos/coins/__init__.py
cryptos/coins/base.py
cryptos/coins/bitcoin.py
cryptos/coins/bitcoin_cash.py
cryptos/coins/bitcoin_gold.py
cryptos/coins/dash.py
cryptos/coins/dogecoin.py
cryptos/coins/litecoin.py
cryptos/electrumx_client/__init__.py
cryptos/electrumx_client/jsonrpc.py
cryptos/electrumx_client/rpc.py
cryptos/electrumx_client/test.py
cryptos/electrumx_client/util.py
cryptos/explorers/__init__.py
cryptos/explorers/base_insight.py
cryptos/explorers/bitpay.py
cryptos/explorers/blockchain.py
cryptos/explorers/blockcypher.py
cryptos/explorers/blockdozer.py
cryptos/explorers/btg_explorer.py
cryptos/explorers/dash_siampm.py
cryptos/explorers/sochain.py
cryptos/explorers/utils.py
pybitcointools23-0.1.1.data/scripts/cryptotool
pybitcointools23-0.1.1.dist-info/LICENSE
pybitcointools23-0.1.1.dist-info/METADATA
pybitcointools23-0.1.1.dist-info/WHEEL
pybitcointools23-0.1.1.dist-info/top_level.txt
pybitcointools23-0.1.1.dist-info/RECORD
