Metadata-Version: 2.1
Name: pybitcointools23
Version: 0.1.1
Summary: A small example package
Home-page: https://github.com/allelementary/pybitcointools
Author: Mikhail Antonov
Author-email: Mikhail Antonov <allelementaryfor@gmail.com>
License: MIT License
Project-URL: Homepage, https://github.com/allelementary/pybitcointools
Project-URL: Bug Tracker, https://github.com/allelementary/pybitcointools/issues
Classifier: Programming Language :: Python :: 3
Classifier: License :: OSI Approved :: MIT License
Classifier: Operating System :: OS Independent
Requires: requests
Requires: pbkdf2
Requires: pycryptodomex
Requires-Python: >=3.8
License-File: LICENSE
